MANIFEST.in
README.md
setup.cfg
setup.py
investpy/__init__.py
investpy/bonds.py
investpy/certificates.py
investpy/commodities.py
investpy/crypto.py
investpy/currency_crosses.py
investpy/etfs.py
investpy/funds.py
investpy/indices.py
investpy/search.py
investpy/stocks.py
investpy.egg-info/PKG-INFO
investpy.egg-info/SOURCES.txt
investpy.egg-info/dependency_links.txt
investpy.egg-info/requires.txt
investpy.egg-info/top_level.txt
investpy/data/__init__.py
investpy/data/bonds_data.py
investpy/data/certificates_data.py
investpy/data/commodities_data.py
investpy/data/crypto_data.py
investpy/data/currency_crosses_data.py
investpy/data/etfs_data.py
investpy/data/funds_data.py
investpy/data/indices_data.py
investpy/data/stocks_data.py
investpy/errors/__init__.py
investpy/resources/__init__.py
investpy/resources/user_agent_list.txt
investpy/resources/bonds/bond_countries.csv
investpy/resources/bonds/bonds.csv
investpy/resources/certificates/certificate_countries.csv
investpy/resources/certificates/certificates.csv
investpy/resources/commodities/commodities.csv
investpy/resources/crypto/cryptos.csv
investpy/resources/currency_crosses/currencies.csv
investpy/resources/currency_crosses/currency_crosses.csv
investpy/resources/etfs/etf_countries.csv
investpy/resources/etfs/etfs.csv
investpy/resources/funds/fund_countries.csv
investpy/resources/funds/funds.csv
investpy/resources/indices/global_indices_countries.csv
investpy/resources/indices/index_countries.csv
investpy/resources/indices/indices.csv
investpy/resources/stocks/stock_countries.csv
investpy/resources/stocks/stocks.csv
investpy/utils/__init__.py
investpy/utils/data.py
investpy/utils/search_obj.py
investpy/utils/user_agent.py
tests/__init__.py
tests/test_investpy.py
tests/test_investpy_errors.py