Metadata-Version: 2.1
Name: investpy
Version: 0.9.13
Summary: investpy — a Python package for financial historical data extraction from Investing
Home-page: https://investpy.readthedocs.io/
Author: Alvaro Bartolome
Author-email: alvarob96@usal.es
License: MIT License
Download-URL: https://github.com/alvarob96/investpy/archive/0.9.13.tar.gz
Project-URL: Bug Reports, https://github.com/alvarob96/investpy/issues
Project-URL: Source, https://github.com/alvarob96/investpy
Project-URL: Documentation, https://investpy.readthedocs.io/
Keywords: investing,investing-api,historical-data,financial-data,stocks,funds,etfs,indices,currency crosses,bonds,commodities,crypto currencies
Platform: UNKNOWN
Classifier: Development Status :: 4 - Beta
Classifier: Programming Language :: Python :: 3 :: Only
Classifier: Programming Language :: Python :: 3.5
Classifier: Programming Language :: Python :: 3.6
Classifier: Programming Language :: Python :: 3.7
Classifier: License :: OSI Approved :: MIT License
Classifier: Intended Audience :: Developers
Classifier: Topic :: Office/Business :: Financial
Classifier: Topic :: Office/Business :: Financial :: Investment
Classifier: Topic :: Scientific/Engineering :: Information Analysis
Classifier: Topic :: Software Development :: Libraries
Requires-Python: >=3
